api/__init__.py
api/user.py
api/utils/__init__.py
api/utils/request.py
api/utils/xcsrf.py
rbxthon-0.1.1.dist-info/LICENSE
rbxthon-0.1.1.dist-info/METADATA
rbxthon-0.1.1.dist-info/WHEEL
rbxthon-0.1.1.dist-info/top_level.txt
rbxthon-0.1.1.dist-info/RECORD
