Metadata-Version: 2.1
Name: rbxthon
Version: 0.1.1
Summary: Open-Source Roblox API built with Python
Home-page: https://github.com/gordxn/Rbxthon
Author: Gordxn
Author-email: 
License: UNKNOWN
Platform: UNKNOWN
Classifier: Programming Language :: Python :: 3
Classifier: License :: OSI Approved :: MIT License
Classifier: Operating System :: OS Independent
Requires-Python: >=3.8
